kozinak/__init__.py
kozinak-0.7.0.dist-info/LICENSE
kozinak-0.7.0.dist-info/METADATA
kozinak-0.7.0.dist-info/WHEEL
kozinak-0.7.0.dist-info/top_level.txt
kozinak-0.7.0.dist-info/RECORD
